{
  "inventory": [
    {
      "id": "4",
      "name": "sor uj mezooo",
      "stock": 50,
      "threshold": 7,
      "imageUrl": "https://brewmanager.blob.core.windows.net/ingredients/95eaaf4b-6085-4305-9f12-8d99194d0d4f.jpg"
    },
    {
      "id": "5",
      "name": "malt",
      "stock": 17,
      "threshold": 7,
      "imageUrl": "asdasd"
    },
    {
      "id": "1",
      "name": "ez",
      "stock": 106,
      "threshold": 7,
      "imageUrl": "https://brewmanager.blob.core.windows.net/ingredients/207a71d9-7a53-489a-96a6-1c04f48fb352.jpg"
    },
    {
      "id": "2",
      "name": "az",
      "stock": 52,
      "threshold": 7,
      "imageUrl": "asdasd"
    },
    {
      "id": "11",
      "name": "malt",
      "stock": 23,
      "threshold": 7,
      "imageUrl": "https://picsum.photos/200"
    },
    {
      "id": "14",
      "name": "barmi",
      "stock": 64,
      "threshold": 2,
      "imageUrl": "https://picsum.photos/200"
    },
    {
      "id": "15",
      "name": "barmi",
      "stock": 31,
      "threshold": 10,
      "imageUrl": "https://picsum.photos/200"
    },
    {
      "id": "16",
      "name": "asd",
      "stock": 97.198,
      "threshold": 3,
      "imageUrl": "https://picsum.photos/200"
    },
    {
      "id": "17",
      "name": "dfdgf",
      "stock": 100,
      "threshold": 4,
      "imageUrl": "https://picsum.photos/200"
    },
    {
      "id": "844c",
      "name": "",
      "stock": 0,
      "threshold": 0,
      "imageUrl": "https://brewmanager.blob.core.windows.net/ingredients/anonym.jpeg"
    },
    {
      "id": "29eb",
      "name": "",
      "stock": 0,
      "threshold": 0,
      "imageUrl": "https://brewmanager.blob.core.windows.net/ingredients/6398eff7-3369-473b-83b9-39bcbab35854.jpg"
    },
    {
      "id": "be2f",
      "name": "",
      "stock": 0,
      "threshold": 0,
      "imageUrl": "asdasd"
    }
  ],
  "recipes": [
    {
      "id": "1",
      "name": "Crazy racoon",
      "ingredients": [
        {
          "id": "2",
          "amount": 3
        },
        {
          "id": "15",
          "amount": 2
        },
        {
          "id": "16",
          "amount": 10.6
        },
        {
          "id": "1",
          "amount": 3
        },
        {
          "id": "17",
          "amount": 15
        },
        {
          "id": "14",
          "amount": 1
        }
      ]
    },
    {
      "id": "2",
      "name": "Fincsa mincsa",
      "ingredients": [
        {
          "id": "2",
          "amount": 3
        },
        {
          "id": "16",
          "amount": 5
        },
        {
          "id": "14",
          "amount": 3
        },
        {
          "id": "15",
          "amount": 2
        },
        {
          "id": "1",
          "amount": 14
        },
        {
          "id": "11",
          "amount": 2
        }
      ]
    },
    {
      "id": "3",
      "name": "Barna sorocske",
      "ingredients": [
        {
          "id": "2",
          "amount": 3
        },
        {
          "id": "11",
          "amount": 2
        },
        {
          "id": "15",
          "amount": 2
        },
        {
          "id": "16",
          "amount": 3
        },
        {
          "id": "14",
          "amount": 3
        },
        {
          "id": "4",
          "amount": 7.09
        }
      ]
    },
    {
      "id": "5",
      "name": "Safe recipe",
      "ingredients": [
        {
          "id": "18",
          "amount": 5
        },
        {
          "id": "4",
          "amount": 2
        },
        {
          "id": "5",
          "amount": 1
        }
      ]
    },
    {
      "id": "0",
      "name": "Valami új",
      "ingredients": [
        {
          "id": "4",
          "amount": 1
        },
        {
          "id": "15",
          "amount": 3
        }
      ]
    }
  ],
  "scheduled-brews": [
    {
      "id": "8",
      "recipe": "2",
      "date": 1679788800000
    },
    {
      "id": "10",
      "recipe": "3",
      "date": 1680220800000
    },
    {
      "id": "11",
      "recipe": "3",
      "date": 1680220800000
    }
  ],
  "users": [
    {
      "login": "admin",
      "password": "admin",
      "id": "1864"
    },
    {
      "login": "cook",
      "password": "cook",
      "id": "6e8f"
    },
    {
      "login": "brewmaster",
      "password": "brewmaster",
      "id": "c9ef"
    }
  ]
}